python_graphql_client/__init__.py
python_graphql_client/graphql_client.py
python_graphql_client-0.4.3.dist-info/LICENSE
python_graphql_client-0.4.3.dist-info/METADATA
python_graphql_client-0.4.3.dist-info/WHEEL
python_graphql_client-0.4.3.dist-info/top_level.txt
python_graphql_client-0.4.3.dist-info/RECORD
