Metadata-Version: 2.1
Name: python-graphql-client
Version: 0.4.3
Summary: Python GraphQL Client
Home-page: https://github.com/prodigyeducation/python-graphql-client
Author: Justin Krinke
Author-email: opensource@prodigygame.com
License: MIT
Keywords: api graphql client
Platform: UNKNOWN
Classifier: Development Status :: 3 - Alpha
Classifier: Intended Audience :: Developers
Classifier: Topic :: Software Development :: Libraries
Classifier: License :: OSI Approved :: MIT License
Classifier: Programming Language :: Python :: 3.6
Classifier: Programming Language :: Python :: 3.7
Classifier: Programming Language :: Python :: 3.8
Provides-Extra: dev
